LICENCE-naruno-gui_lib__.md
LICENCE-naruno-lib-kot__.md
LICENCE-naruno-lib-mix__.md
LICENCE-naruno-wallet-elipticcurve__.md
LICENSE-others__.md
MANIFEST.in
README.md
setup.py
naruno/__init__.py
naruno/config.py
naruno.egg-info/PKG-INFO
naruno.egg-info/SOURCES.txt
naruno.egg-info/dependency_links.txt
naruno.egg-info/entry_points.txt
naruno.egg-info/top_level.txt
naruno/accounts/account.py
naruno/accounts/get_accounts.py
naruno/accounts/get_balance.py
naruno/accounts/get_sequence_number.py
naruno/accounts/save_accounts.py
naruno/accounts/commanders/delete_commander.py
naruno/accounts/commanders/get_comnder.py
naruno/accounts/commanders/save_commander.py
naruno/api/main.py
naruno/api/buildozer/main.py
naruno/apps/checker.py
naruno/apps/remote_app.py
naruno/blockchain/block/block_main.py
naruno/blockchain/block/blocks_hash.py
naruno/blockchain/block/change_transaction_fee.py
naruno/blockchain/block/create_block.py
naruno/blockchain/block/get_block.py
naruno/blockchain/block/get_block_from_blockchain_db.py
naruno/blockchain/block/get_minumum_transfer_amount.py
naruno/blockchain/block/just_one_tx.py
naruno/blockchain/block/max_data_size.py
naruno/blockchain/block/max_tx_number.py
naruno/blockchain/block/save_block.py
naruno/blockchain/block/save_block_to_blockchain_db.py
naruno/blockchain/block/shares.py
naruno/blockchain/block/hash/accounts_hash.py
naruno/blockchain/block/hash/blocks_hash.py
naruno/blockchain/block/hash/calculate_hash.py
naruno/blockchain/block/hash/tx_hash.py
naruno/blockchain/candidate_block/candidate_block_main.py
naruno/cli/main.py
naruno/consensus/consensus_main.py
naruno/consensus/finished/finished_main.py
naruno/consensus/finished/transactions/transactions_main.py
naruno/consensus/finished/true_time/true_time_main.py
naruno/consensus/ongoing/ongoing_main.py
naruno/consensus/rounds/round_1/round_1_main.py
naruno/consensus/rounds/round_1/checks/checks_main.py
naruno/consensus/rounds/round_1/checks/candidate_blocks/candidate_blocks_main.py
naruno/consensus/rounds/round_1/checks/time/time_difference/time_difference_main.py
naruno/consensus/rounds/round_1/process/process_main.py
