Metadata-Version: 2.1
Name: naruno
Version: 0.60.4
Summary: Naruno is a lightning-fast, secure, and scalable blockchain that is able to create transaction proofs and verification via raw data and timestamp. We remove the archive nodes and lazy web3 integrations. With Naruno everyone can get the proof (5-10MB) of their transactions via their nodes and after everyone can use in another node for verification the raw data and timestamp. Also you can integrate your web3 applications with 4 code lines (just python for now) via our remote app system.
Home-page: https://github.com/Naruno/Naruno
Author: Naruno Developers
Author-email: onur.atakan.ulusoy@naruno.org
License: MPL-2.0
Keywords: python,cryptography,blockchain,p2p,python3,cryptocurrency,kivy,coin,copilot,fba,dapps,p2p-network,kivymd,blokzinciri,naruno,githubcopilot,blokzincir
Platform: UNKNOWN
Classifier: Development Status :: 3 - Alpha
Classifier: License :: OSI Approved :: Mozilla Public License 2.0 (MPL 2.0)
Classifier: Programming Language :: Python :: 3
Requires-Python: >=3.8
